README.md
setup.py
easy_python/__init__.py
easy_python/easy.py
easy_python.egg-info/PKG-INFO
easy_python.egg-info/SOURCES.txt
easy_python.egg-info/dependency_links.txt
easy_python.egg-info/top_level.txt