Metadata-Version: 2.1
Name: easy-python
Version: 0.1
Summary: Esta es la descripcion de mi paquete
Home-page: https://github.com/PinaYTTT/easy_python
Author: PinaYT
Author-email: pinacomandos@gmail.com
License: MIT
Download-URL: https://github.com/PinaYTTT/easy_python/tree/0.1
Keywords: testing,logging,example
Platform: UNKNOWN
